hyperstruct/__init__.py
hyperstruct/__main__.py
hyperstruct/fuselage.py
hyperstruct/py.typed
hyperstruct-0.0.10.dist-info/LICENSE
hyperstruct-0.0.10.dist-info/METADATA
hyperstruct-0.0.10.dist-info/WHEEL
hyperstruct-0.0.10.dist-info/entry_points.txt
hyperstruct-0.0.10.dist-info/RECORD
