Metadata-Version: 2.3
Name: hyperstruct
Version: 0.0.10
Summary: Hyperstruct
Home-page: https://github.com/czarified/hyperstruct
License: MIT
Author: Benjamin Crews
Author-email: aceF22@gmail.com
Requires-Python: >=3.10,<4.0
Classifier: Development Status :: 1 - Planning
Classifier: License :: OSI Approved :: MIT License
Classifier: Programming Language :: Python :: 3
Classifier: Programming Language :: Python :: 3.10
Classifier: Programming Language :: Python :: 3.11
Classifier: Programming Language :: Python :: 3.12
Classifier: Programming Language :: Python :: 3.13
Requires-Dist: click (>=8.0.1,<9.0)
Requires-Dist: matplotlib (>=3.10.1,<4.0)
Requires-Dist: numpy (>=2.0,<3.0)
Requires-Dist: pandas (>=2.3.0,<3.0)
Requires-Dist: pytest-check (>=2.5.3,<3.0)
Requires-Dist: scipy (>=1.14.1,<2.0)
Project-URL: Changelog, https://github.com/czarified/hyperstruct/releases
Project-URL: Documentation, https://hyperstruct.readthedocs.io
Project-URL: Repository, https://github.com/czarified/hyperstruct
